{
  "namespaces": {
    "zombie.core.math": {
      "Matrix4": {
        "constructors": [
          {
            "modifiers": [
              "public"
            ],
            "parameters": [
              {
                "name": "m00",
                "type": {
                  "basic": "float"
                }
              },
              {
                "name": "m01",
                "type": {
                  "basic": "float"
                }
              },
              {
                "name": "m02",
                "type": {
                  "basic": "float"
                }
              },
              {
                "name": "m03",
                "type": {
                  "basic": "float"
                }
              },
              {
                "name": "m10",
                "type": {
                  "basic": "float"
                }
              },
              {
                "name": "m11",
                "type": {
                  "basic": "float"
                }
              },
              {
                "name": "m12",
                "type": {
                  "basic": "float"
                }
              },
              {
                "name": "m13",
                "type": {
                  "basic": "float"
                }
              },
              {
                "name": "m20",
                "type": {
                  "basic": "float"
                }
              },
              {
                "name": "m21",
                "type": {
                  "basic": "float"
                }
              },
              {
                "name": "m22",
                "type": {
                  "basic": "float"
                }
              },
              {
                "name": "m23",
                "type": {
                  "basic": "float"
                }
              },
              {
                "name": "m30",
                "type": {
                  "basic": "float"
                }
              },
              {
                "name": "m31",
                "type": {
                  "basic": "float"
                }
              },
              {
                "name": "m32",
                "type": {
                  "basic": "float"
                }
              },
              {
                "name": "m33",
                "type": {
                  "basic": "float"
                }
              }
            ]
          },
          {
            "modifiers": [
              "public"
            ],
            "parameters": [
              {
                "name": "m",
                "type": {
                  "basic": "Matrix4"
                }
              }
            ]
          }
        ],
        "methods": [
          {
            "name": "Get",
            "modifiers": [
              "public"
            ],
            "returns": {
              "type": {
                "basic": "org.lwjgl.util.vector.Matrix4f"
              }
            }
          },
          {
            "name": "Set",
            "modifiers": [
              "public"
            ],
            "parameters": [
              {
                "name": "m",
                "type": {
                  "basic": "org.lwjgl.util.vector.Matrix4f"
                }
              }
            ],
            "returns": {
              "type": {
                "basic": "void"
              }
            }
          }
        ],
        "modifiers": [
          "public",
          "final"
        ],
        "javaType": "class"
      },
      "PZMath": {
        "fields": {
          "degToRads": {
            "name": "degToRads",
            "modifiers": [
              "public",
              "static",
              "final"
            ],
            "type": {
              "basic": "float"
            },
            "notes": "Conversion ratios, Degrees to Radians and back"
          },
          "microsToNanos": {
            "name": "microsToNanos",
            "modifiers": [
              "public",
              "static",
              "final"
            ],
            "type": {
              "basic": "long"
            }
          },
          "millisToMicros": {
            "name": "millisToMicros",
            "modifiers": [
              "public",
              "static",
              "final"
            ],
            "type": {
              "basic": "long"
            }
          },
          "PI": {
            "name": "PI",
            "modifiers": [
              "public",
              "static",
              "final"
            ],
            "type": {
              "basic": "float"
            },
            "notes": "The double value that is closer than any other to\n pi, the ratio of the circumference of a circle to its\n diameter."
          },
          "PI2": {
            "name": "PI2",
            "modifiers": [
              "public",
              "static",
              "final"
            ],
            "type": {
              "basic": "float"
            }
          },
          "radToDegs": {
            "name": "radToDegs",
            "modifiers": [
              "public",
              "static",
              "final"
            ],
            "type": {
              "basic": "float"
            }
          },
          "secondsToMillis": {
            "name": "secondsToMillis",
            "modifiers": [
              "public",
              "static",
              "final"
            ],
            "type": {
              "basic": "long"
            }
          },
          "secondsToNanos": {
            "name": "secondsToNanos",
            "modifiers": [
              "public",
              "static"
            ],
            "type": {
              "basic": "long"
            }
          }
        },
        "constructors": [
          {
            "modifiers": [
              "public"
            ]
          }
        ],
        "methods": [
          {
            "name": "abs",
            "modifiers": [
              "public",
              "static"
            ],
            "parameters": [
              {
                "name": "val",
                "type": {
                  "basic": "float"
                }
              }
            ],
            "returns": {
              "type": {
                "basic": "float"
              }
            }
          },
          {
            "name": "almostIdentity",
            "modifiers": [
              "public",
              "static"
            ],
            "parameters": [
              {
                "name": "x",
                "type": {
                  "basic": "float"
                },
                "notes": "value in [0..1]"
              },
              {
                "name": "m",
                "type": {
                  "basic": "float"
                }
              },
              {
                "name": "n",
                "type": {
                  "basic": "float"
                }
              }
            ],
            "returns": {
              "type": {
                "basic": "float"
              },
              "notes": "value in [0..1]"
            },
            "notes": "Almost Identity\n\n Imagine you don't want to modify a signal unless it's drops to zero or close to it, in which case you want\n to replace the value with a small possitive constant. Then, rather than clamping the value and introduce\n a discontinuity, you can smoothly blend the signal into the desired clipped value. So, let m be the threshold\n (anything above m stays unchanged), and n the value things will take when the signal is zero.\n Then, the following function does the soft clipping (in a cubic fashion):\n\n https://iquilezles.org/www/articles/functions/functions.htm"
          },
          {
            "name": "almostUnitIdentity",
            "modifiers": [
              "public",
              "static"
            ],
            "parameters": [
              {
                "name": "x",
                "type": {
                  "basic": "float"
                },
                "notes": "value in [0..1]"
              }
            ],
            "returns": {
              "type": {
                "basic": "float"
              },
              "notes": "value in [0..1]"
            },
            "notes": "Almost Unit Identity\n\n This is a near-identiy function that maps the unit interval into itself. It is the cousin of smoothstep(), in\n that it maps 0 to 0, 1 to 1, and has a 0 derivative at the origin, just like smoothstep. However, instead of\n having a 0 derivative at 1, it has a derivative of 1 at that point. It's equivalent to the Almost Identiy above\n with n=0 and m=1. Since it's a cubic just like smoothstep() it is very fast to evaluate.\n\n https://iquilezles.org/www/articles/functions/functions.htm"
          },
          {
            "name": "c_lerp",
            "modifiers": [
              "public",
              "static"
            ],
            "parameters": [
              {
                "name": "src",
                "type": {
                  "basic": "float"
                }
              },
              {
                "name": "dest",
                "type": {
                  "basic": "float"
                }
              },
              {
                "name": "alpha",
                "type": {
                  "basic": "float"
                }
              }
            ],
            "returns": {
              "type": {
                "basic": "float"
              }
            }
          },
          {
            "name": "canParseFloat",
            "modifiers": [
              "public",
              "static"
            ],
            "parameters": [
              {
                "name": "varStr",
                "type": {
                  "basic": "String"
                }
              }
            ],
            "returns": {
              "type": {
                "basic": "boolean"
              }
            }
          },
          {
            "name": "ceil",
            "modifiers": [
              "public",
              "static"
            ],
            "parameters": [
              {
                "name": "val",
                "type": {
                  "basic": "float"
                }
              }
            ],
            "returns": {
              "type": {
                "basic": "float"
              }
            }
          },
          {
            "name": "clamp",
            "modifiers": [
              "public",
              "static"
            ],
            "parameters": [
              {
                "name": "val",
                "type": {
                  "basic": "float"
                }
              },
              {
                "name": "min",
                "type": {
                  "basic": "float"
                }
              },
              {
                "name": "max",
                "type": {
                  "basic": "float"
                }
              }
            ],
            "returns": {
              "type": {
                "basic": "float"
              },
              "notes": "min <= val <= max"
            },
            "notes": "Result is clamped between min and max."
          },
          {
            "name": "clamp",
            "modifiers": [
              "public",
              "static"
            ],
            "parameters": [
              {
                "name": "val",
                "type": {
                  "basic": "long"
                }
              },
              {
                "name": "min",
                "type": {
                  "basic": "long"
                }
              },
              {
                "name": "max",
                "type": {
                  "basic": "long"
                }
              }
            ],
            "returns": {
              "type": {
                "basic": "long"
              }
            }
          },
          {
            "name": "clamp",
            "modifiers": [
              "public",
              "static"
            ],
            "parameters": [
              {
                "name": "val",
                "type": {
                  "basic": "int"
                }
              },
              {
                "name": "min",
                "type": {
                  "basic": "int"
                }
              },
              {
                "name": "max",
                "type": {
                  "basic": "int"
                }
              }
            ],
            "returns": {
              "type": {
                "basic": "int"
              },
              "notes": "min <= val <= max"
            },
            "notes": "Result is clamped between min and max."
          },
          {
            "name": "clamp_01",
            "modifiers": [
              "public",
              "static"
            ],
            "parameters": [
              {
                "name": "val",
                "type": {
                  "basic": "float"
                }
              }
            ],
            "returns": {
              "type": {
                "basic": "float"
              }
            }
          },
          {
            "name": "clampFloat",
            "modifiers": [
              "public",
              "static"
            ],
            "parameters": [
              {
                "name": "val",
                "type": {
                  "basic": "float"
                }
              },
              {
                "name": "min",
                "type": {
                  "basic": "float"
                }
              },
              {
                "name": "max",
                "type": {
                  "basic": "float"
                }
              }
            ],
            "returns": {
              "type": {
                "basic": "float"
              }
            }
          },
          {
            "name": "convertMatrix",
            "modifiers": [
              "public",
              "static"
            ],
            "parameters": [
              {
                "name": "src",
                "type": {
                  "basic": "org.joml.Matrix4f"
                }
              },
              {
                "name": "dst",
                "type": {
                  "basic": "org.lwjgl.util.vector.Matrix4f"
                }
              }
            ],
            "returns": {
              "type": {
                "basic": "org.lwjgl.util.vector.Matrix4f"
              }
            }
          },
          {
            "name": "convertMatrix",
            "modifiers": [
              "public",
              "static"
            ],
            "parameters": [
              {
                "name": "src",
                "type": {
                  "basic": "org.lwjgl.util.vector.Matrix4f"
                }
              },
              {
                "name": "dst",
                "type": {
                  "basic": "org.joml.Matrix4f"
                }
              }
            ],
            "returns": {
              "type": {
                "basic": "org.joml.Matrix4f"
              }
            }
          },
          {
            "name": "degToRad",
            "modifiers": [
              "public",
              "static"
            ],
            "parameters": [
              {
                "name": "degrees",
                "type": {
                  "basic": "float"
                }
              }
            ],
            "returns": {
              "type": {
                "basic": "float"
              }
            }
          },
          {
            "name": "equal",
            "modifiers": [
              "public",
              "static"
            ],
            "parameters": [
              {
                "name": "a",
                "type": {
                  "basic": "float"
                }
              },
              {
                "name": "b",
                "type": {
                  "basic": "float"
                }
              }
            ],
            "returns": {
              "type": {
                "basic": "boolean"
              }
            }
          },
          {
            "name": "equal",
            "modifiers": [
              "public",
              "static"
            ],
            "parameters": [
              {
                "name": "a",
                "type": {
                  "basic": "float"
                }
              },
              {
                "name": "b",
                "type": {
                  "basic": "float"
                }
              },
              {
                "name": "delta",
                "type": {
                  "basic": "float"
                }
              }
            ],
            "returns": {
              "type": {
                "basic": "boolean"
              }
            }
          },
          {
            "name": "fastfloor",
            "modifiers": [
              "public",
              "static"
            ],
            "parameters": [
              {
                "name": "x",
                "type": {
                  "basic": "double"
                }
              }
            ],
            "returns": {
              "type": {
                "basic": "int"
              }
            }
          },
          {
            "name": "fastfloor",
            "modifiers": [
              "public",
              "static"
            ],
            "parameters": [
              {
                "name": "x",
                "type": {
                  "basic": "float"
                }
              }
            ],
            "returns": {
              "type": {
                "basic": "int"
              }
            }
          },
          {
            "name": "floor",
            "modifiers": [
              "public",
              "static"
            ],
            "parameters": [
              {
                "name": "val",
                "type": {
                  "basic": "float"
                }
              }
            ],
            "returns": {
              "type": {
                "basic": "float"
              }
            }
          },
          {
            "name": "frac",
            "modifiers": [
              "public",
              "static"
            ],
            "parameters": [
              {
                "name": "val",
                "type": {
                  "basic": "float"
                }
              }
            ],
            "returns": {
              "type": {
                "basic": "float"
              }
            }
          },
          {
            "name": "gain",
            "modifiers": [
              "public",
              "static"
            ],
            "parameters": [
              {
                "name": "x",
                "type": {
                  "basic": "float"
                }
              },
              {
                "name": "k",
                "type": {
                  "basic": "float"
                }
              }
            ],
            "returns": {
              "type": {
                "basic": "float"
              }
            },
            "notes": "Gain\n\n Remapping the unit interval into the unit interval by expanding the sides and compressing the center, and\n keeping 1/2 mapped to 1/2, that can be done with the gain() function. This was a common function in RSL tutorials\n (the Renderman Shading Language). k=1 is the identity curve, k<1 produces the classic gain() shape, and k>1\n produces \"s\" shaped curces. The curves are symmetric (and inverse) for k=a and k=1/a.\n\n https://iquilezles.org/www/articles/functions/functions.htm"
          },
          {
            "name": "getClosestAngle",
            "modifiers": [
              "public",
              "static"
            ],
            "parameters": [
              {
                "name": "in_radsA",
                "type": {
                  "basic": "float"
                }
              },
              {
                "name": "in_radsB",
                "type": {
                  "basic": "float"
                }
              }
            ],
            "returns": {
              "type": {
                "basic": "float"
              }
            }
          },
          {
            "name": "getClosestAngleDegrees",
            "modifiers": [
              "public",
              "static"
            ],
            "parameters": [
              {
                "name": "in_degsA",
                "type": {
                  "basic": "float"
                }
              },
              {
                "name": "in_degsB",
                "type": {
                  "basic": "float"
                }
              }
            ],
            "returns": {
              "type": {
                "basic": "float"
              }
            }
          },
          {
            "name": "lerp",
            "modifiers": [
              "public",
              "static"
            ],
            "parameters": [
              {
                "name": "src",
                "type": {
                  "basic": "float"
                }
              },
              {
                "name": "dest",
                "type": {
                  "basic": "float"
                }
              },
              {
                "name": "alpha",
                "type": {
                  "basic": "float"
                }
              }
            ],
            "returns": {
              "type": {
                "basic": "float"
              }
            }
          },
          {
            "name": "lerp",
            "modifiers": [
              "public",
              "static"
            ],
            "parameters": [
              {
                "name": "out",
                "type": {
                  "basic": "org.lwjgl.util.vector.Vector3f"
                }
              },
              {
                "name": "a",
                "type": {
                  "basic": "org.lwjgl.util.vector.Vector3f"
                }
              },
              {
                "name": "b",
                "type": {
                  "basic": "org.lwjgl.util.vector.Vector3f"
                }
              },
              {
                "name": "t",
                "type": {
                  "basic": "float"
                }
              }
            ],
            "returns": {
              "type": {
                "basic": "org.lwjgl.util.vector.Vector3f"
              }
            }
          },
          {
            "name": "lerp",
            "modifiers": [
              "public",
              "static"
            ],
            "parameters": [
              {
                "name": "out",
                "type": {
                  "basic": "Vector2"
                }
              },
              {
                "name": "a",
                "type": {
                  "basic": "Vector2"
                }
              },
              {
                "name": "b",
                "type": {
                  "basic": "Vector2"
                }
              },
              {
                "name": "t",
                "type": {
                  "basic": "float"
                }
              }
            ],
            "returns": {
              "type": {
                "basic": "Vector2"
              }
            }
          },
          {
            "name": "lerpAngle",
            "modifiers": [
              "public",
              "static"
            ],
            "parameters": [
              {
                "name": "src",
                "type": {
                  "basic": "float"
                }
              },
              {
                "name": "dest",
                "type": {
                  "basic": "float"
                }
              },
              {
                "name": "alpha",
                "type": {
                  "basic": "float"
                }
              }
            ],
            "returns": {
              "type": {
                "basic": "float"
              }
            }
          },
          {
            "name": "lerpFunc_EaseInQuad",
            "modifiers": [
              "public",
              "static"
            ],
            "parameters": [
              {
                "name": "x",
                "type": {
                  "basic": "float"
                }
              }
            ],
            "returns": {
              "type": {
                "basic": "float"
              }
            }
          },
          {
            "name": "lerpFunc_EaseOutInQuad",
            "modifiers": [
              "public",
              "static"
            ],
            "parameters": [
              {
                "name": "x",
                "type": {
                  "basic": "float"
                }
              }
            ],
            "returns": {
              "type": {
                "basic": "float"
              }
            }
          },
          {
            "name": "lerpFunc_EaseOutQuad",
            "modifiers": [
              "public",
              "static"
            ],
            "parameters": [
              {
                "name": "x",
                "type": {
                  "basic": "float"
                }
              }
            ],
            "returns": {
              "type": {
                "basic": "float"
              }
            }
          },
          {
            "name": "max",
            "modifiers": [
              "public",
              "static"
            ],
            "parameters": [
              {
                "name": "a",
                "type": {
                  "basic": "float"
                }
              },
              {
                "name": "b",
                "type": {
                  "basic": "float"
                }
              }
            ],
            "returns": {
              "type": {
                "basic": "float"
              }
            }
          },
          {
            "name": "max",
            "modifiers": [
              "public",
              "static"
            ],
            "parameters": [
              {
                "name": "a",
                "type": {
                  "basic": "int"
                }
              },
              {
                "name": "b",
                "type": {
                  "basic": "int"
                }
              }
            ],
            "returns": {
              "type": {
                "basic": "int"
              }
            }
          },
          {
            "name": "min",
            "modifiers": [
              "public",
              "static"
            ],
            "parameters": [
              {
                "name": "a",
                "type": {
                  "basic": "float"
                }
              },
              {
                "name": "b",
                "type": {
                  "basic": "float"
                }
              }
            ],
            "returns": {
              "type": {
                "basic": "float"
              }
            }
          },
          {
            "name": "min",
            "modifiers": [
              "public",
              "static"
            ],
            "parameters": [
              {
                "name": "a",
                "type": {
                  "basic": "int"
                }
              },
              {
                "name": "b",
                "type": {
                  "basic": "int"
                }
              }
            ],
            "returns": {
              "type": {
                "basic": "int"
              }
            }
          },
          {
            "name": "radToDeg",
            "modifiers": [
              "public",
              "static"
            ],
            "parameters": [
              {
                "name": "radians",
                "type": {
                  "basic": "float"
                }
              }
            ],
            "returns": {
              "type": {
                "basic": "float"
              }
            }
          },
          {
            "name": "roundFromEdges",
            "modifiers": [
              "public",
              "static"
            ],
            "parameters": [
              {
                "name": "val",
                "type": {
                  "basic": "float"
                }
              }
            ],
            "returns": {
              "type": {
                "basic": "float"
              }
            }
          },
          {
            "name": "roundToInt",
            "modifiers": [
              "public",
              "static"
            ],
            "parameters": [
              {
                "name": "val",
                "type": {
                  "basic": "float"
                }
              }
            ],
            "returns": {
              "type": {
                "basic": "int"
              }
            }
          },
          {
            "name": "roundToIntPlus05",
            "modifiers": [
              "public",
              "static"
            ],
            "parameters": [
              {
                "name": "val",
                "type": {
                  "basic": "float"
                }
              }
            ],
            "returns": {
              "type": {
                "basic": "float"
              }
            }
          },
          {
            "name": "roundToNearest",
            "modifiers": [
              "public",
              "static"
            ],
            "parameters": [
              {
                "name": "val",
                "type": {
                  "basic": "float"
                }
              }
            ],
            "returns": {
              "type": {
                "basic": "float"
              }
            }
          },
          {
            "name": "sign",
            "modifiers": [
              "public",
              "static"
            ],
            "parameters": [
              {
                "name": "val",
                "type": {
                  "basic": "float"
                }
              }
            ],
            "returns": {
              "type": {
                "basic": "int"
              }
            }
          },
          {
            "name": "slerp",
            "modifiers": [
              "public",
              "static"
            ],
            "parameters": [
              {
                "name": "result",
                "type": {
                  "basic": "org.lwjgl.util.vector.Quaternion"
                }
              },
              {
                "name": "from",
                "type": {
                  "basic": "org.lwjgl.util.vector.Quaternion"
                }
              },
              {
                "name": "to",
                "type": {
                  "basic": "org.lwjgl.util.vector.Quaternion"
                }
              },
              {
                "name": "alpha",
                "type": {
                  "basic": "float"
                }
              }
            ],
            "returns": {
              "type": {
                "basic": "org.lwjgl.util.vector.Quaternion"
              }
            }
          },
          {
            "name": "sqrt",
            "modifiers": [
              "public",
              "static"
            ],
            "parameters": [
              {
                "name": "val",
                "type": {
                  "basic": "float"
                }
              }
            ],
            "returns": {
              "type": {
                "basic": "float"
              }
            }
          },
          {
            "name": "step",
            "modifiers": [
              "public",
              "static"
            ],
            "parameters": [
              {
                "name": "from",
                "type": {
                  "basic": "float"
                }
              },
              {
                "name": "to",
                "type": {
                  "basic": "float"
                }
              },
              {
                "name": "delta",
                "type": {
                  "basic": "float"
                }
              }
            ],
            "returns": {
              "type": {
                "basic": "float"
              }
            }
          },
          {
            "name": "testSideOfLine",
            "modifiers": [
              "public",
              "static"
            ],
            "parameters": [
              {
                "name": "x1",
                "type": {
                  "basic": "float"
                }
              },
              {
                "name": "y1",
                "type": {
                  "basic": "float"
                }
              },
              {
                "name": "x2",
                "type": {
                  "basic": "float"
                }
              },
              {
                "name": "y2",
                "type": {
                  "basic": "float"
                }
              },
              {
                "name": "px",
                "type": {
                  "basic": "float"
                }
              },
              {
                "name": "py",
                "type": {
                  "basic": "float"
                }
              }
            ],
            "returns": {
              "type": {
                "basic": "PZMath.SideOfLine"
              }
            }
          },
          {
            "name": "tryParseDouble",
            "modifiers": [
              "public",
              "static"
            ],
            "parameters": [
              {
                "name": "varStr",
                "type": {
                  "basic": "String"
                }
              },
              {
                "name": "defaultVal",
                "type": {
                  "basic": "double"
                }
              }
            ],
            "returns": {
              "type": {
                "basic": "double"
              }
            }
          },
          {
            "name": "tryParseFloat",
            "modifiers": [
              "public",
              "static"
            ],
            "parameters": [
              {
                "name": "varStr",
                "type": {
                  "basic": "String"
                }
              },
              {
                "name": "defaultVal",
                "type": {
                  "basic": "float"
                }
              }
            ],
            "returns": {
              "type": {
                "basic": "float"
              }
            }
          },
          {
            "name": "tryParseInt",
            "modifiers": [
              "public",
              "static"
            ],
            "parameters": [
              {
                "name": "varStr",
                "type": {
                  "basic": "String"
                }
              },
              {
                "name": "defaultVal",
                "type": {
                  "basic": "int"
                }
              }
            ],
            "returns": {
              "type": {
                "basic": "int"
              }
            }
          },
          {
            "name": "wrap",
            "modifiers": [
              "public",
              "static"
            ],
            "parameters": [
              {
                "name": "val",
                "type": {
                  "basic": "float"
                }
              },
              {
                "name": "range",
                "type": {
                  "basic": "float"
                }
              }
            ],
            "returns": {
              "type": {
                "basic": "float"
              }
            }
          },
          {
            "name": "wrap",
            "modifiers": [
              "public",
              "static"
            ],
            "parameters": [
              {
                "name": "in_val",
                "type": {
                  "basic": "float"
                }
              },
              {
                "name": "in_min",
                "type": {
                  "basic": "float"
                }
              },
              {
                "name": "in_max",
                "type": {
                  "basic": "float"
                }
              }
            ],
            "returns": {
              "type": {
                "basic": "float"
              }
            }
          }
        ],
        "modifiers": [
          "public",
          "final"
        ],
        "javaType": "class",
        "extends": "Object"
      },
      "PZMath.SideOfLine": {
        "fields": {
          "Left": {
            "name": "Left",
            "modifiers": [
              "public",
              "static",
              "final"
            ],
            "type": {
              "basic": "PZMath.SideOfLine"
            }
          },
          "OnLine": {
            "name": "OnLine",
            "modifiers": [
              "public",
              "static",
              "final"
            ],
            "type": {
              "basic": "PZMath.SideOfLine"
            }
          },
          "Right": {
            "name": "Right",
            "modifiers": [
              "public",
              "static",
              "final"
            ],
            "type": {
              "basic": "PZMath.SideOfLine"
            }
          }
        },
        "methods": [
          {
            "name": "values",
            "modifiers": [
              "public",
              "static"
            ],
            "returns": {
              "type": {
                "basic": "PZMath.SideOfLine"
              },
              "notes": "an array containing the constants of this enum class, in the order they are declared"
            },
            "notes": "Returns an array containing the constants of this enum class, in\nthe order they are declared."
          }
        ],
        "modifiers": [
          "public",
          "static"
        ],
        "javaType": "enum",
        "extends": "Enum"
      },
      "Vector3": {
        "constructors": [
          {
            "modifiers": [
              "public"
            ]
          },
          {
            "modifiers": [
              "public"
            ],
            "parameters": [
              {
                "name": "x",
                "type": {
                  "basic": "float"
                }
              },
              {
                "name": "y",
                "type": {
                  "basic": "float"
                }
              },
              {
                "name": "z",
                "type": {
                  "basic": "float"
                }
              }
            ]
          },
          {
            "modifiers": [
              "public"
            ],
            "parameters": [
              {
                "name": "v",
                "type": {
                  "basic": "org.lwjgl.util.vector.Vector3f"
                }
              }
            ]
          },
          {
            "modifiers": [
              "public"
            ],
            "parameters": [
              {
                "name": "v",
                "type": {
                  "basic": "Vector3"
                }
              }
            ]
          }
        ],
        "methods": [
          {
            "name": "addScaled",
            "modifiers": [
              "public",
              "static"
            ],
            "parameters": [
              {
                "name": "a",
                "type": {
                  "basic": "org.lwjgl.util.vector.Vector3f"
                }
              },
              {
                "name": "b",
                "type": {
                  "basic": "org.lwjgl.util.vector.Vector3f"
                }
              },
              {
                "name": "scale",
                "type": {
                  "basic": "float"
                }
              },
              {
                "name": "result",
                "type": {
                  "basic": "org.lwjgl.util.vector.Vector3f"
                }
              }
            ],
            "returns": {
              "type": {
                "basic": "org.lwjgl.util.vector.Vector3f"
              },
              "notes": "The supplied result vector."
            },
            "notes": "Result = a + b * scale"
          },
          {
            "name": "cross",
            "modifiers": [
              "public"
            ],
            "parameters": [
              {
                "name": "vec",
                "type": {
                  "basic": "Vector3"
                }
              }
            ],
            "returns": {
              "type": {
                "basic": "Vector3"
              }
            }
          },
          {
            "name": "dot",
            "modifiers": [
              "public"
            ],
            "parameters": [
              {
                "name": "vec",
                "type": {
                  "basic": "Vector3"
                }
              }
            ],
            "returns": {
              "type": {
                "basic": "float"
              }
            }
          },
          {
            "name": "Get",
            "modifiers": [
              "public"
            ],
            "returns": {
              "type": {
                "basic": "org.lwjgl.util.vector.Vector3f"
              }
            }
          },
          {
            "name": "reset",
            "modifiers": [
              "public"
            ],
            "returns": {
              "type": {
                "basic": "Vector3"
              }
            }
          },
          {
            "name": "Set",
            "modifiers": [
              "public"
            ],
            "parameters": [
              {
                "name": "v",
                "type": {
                  "basic": "org.lwjgl.util.vector.Vector3f"
                }
              }
            ],
            "returns": {
              "type": {
                "basic": "void"
              }
            }
          },
          {
            "name": "setScaled",
            "modifiers": [
              "public",
              "static"
            ],
            "parameters": [
              {
                "name": "a",
                "type": {
                  "basic": "org.lwjgl.util.vector.Vector3f"
                }
              },
              {
                "name": "scale",
                "type": {
                  "basic": "float"
                }
              },
              {
                "name": "result",
                "type": {
                  "basic": "org.lwjgl.util.vector.Vector3f"
                }
              }
            ],
            "returns": {
              "type": {
                "basic": "org.lwjgl.util.vector.Vector3f"
              },
              "notes": "The supplied result vector."
            },
            "notes": "Result = a * scale"
          }
        ],
        "modifiers": [
          "public"
        ],
        "javaType": "class"
      },
      "Vector4": {
        "constructors": [
          {
            "modifiers": [
              "public"
            ]
          },
          {
            "modifiers": [
              "public"
            ],
            "parameters": [
              {
                "name": "x",
                "type": {
                  "basic": "float"
                }
              },
              {
                "name": "y",
                "type": {
                  "basic": "float"
                }
              },
              {
                "name": "z",
                "type": {
                  "basic": "float"
                }
              },
              {
                "name": "w",
                "type": {
                  "basic": "float"
                }
              }
            ]
          },
          {
            "modifiers": [
              "public"
            ],
            "parameters": [
              {
                "name": "v",
                "type": {
                  "basic": "org.lwjgl.util.vector.Vector4f"
                }
              }
            ]
          }
        ],
        "methods": [
          {
            "name": "Get",
            "modifiers": [
              "public"
            ],
            "returns": {
              "type": {
                "basic": "org.lwjgl.util.vector.Vector4f"
              }
            }
          },
          {
            "name": "Set",
            "modifiers": [
              "public"
            ],
            "parameters": [
              {
                "name": "v",
                "type": {
                  "basic": "org.lwjgl.util.vector.Vector4f"
                }
              }
            ],
            "returns": {
              "type": {
                "basic": "void"
              }
            }
          }
        ],
        "modifiers": [
          "public"
        ],
        "javaType": "class"
      }
    }
  }
}